setup.py
choiceinput/__init__.py
choiceinput/widgets.py
django_choiceinput.egg-info/PKG-INFO
django_choiceinput.egg-info/SOURCES.txt
django_choiceinput.egg-info/dependency_links.txt
django_choiceinput.egg-info/requires.txt
django_choiceinput.egg-info/top_level.txt