Metadata-Version: 1.0
Name: django-choiceinput
Version: 0.1.0
Summary: Display preset strings as select tag right beside TextInput widget in Django
Home-page: http://github.com/lqez/django-choiceinput
Author: Park, Hyunwoo
Author-email: ez.amiryo@gmail.com
License: UNKNOWN
Platform: UNKNOWN
Classifier: Topic :: Utilities
Classifier: Topic :: Internet :: WWW/HTTP
Classifier: Topic :: Software Development :: Libraries :: Python Modules
Classifier: Environment :: Web Environment
Classifier: Framework :: Django
Classifier: Development Status :: 3 - Alpha
Classifier: Intended Audience :: Developers
Classifier: Programming Language :: Python
Classifier: License :: OSI Approved :: MIT License
